messagehub/__init__.py
messagehub/core/__init__.py
messagehub/core/client.py
messagehub/core/messagehub.py
messagehub/util/__init__.py
messagehub/util/formula.py
messagehub/util/upass.py
messagehub-0.1.2.dist-info/LICENSE
messagehub-0.1.2.dist-info/METADATA
messagehub-0.1.2.dist-info/WHEEL
messagehub-0.1.2.dist-info/top_level.txt
messagehub-0.1.2.dist-info/RECORD
