Metadata-Version: 2.1
Name: messagehub
Version: 0.1.2
Summary: messagehub: crypto and traditional financial data hub
Home-page: https://github.com/chaininout/messagehub
Author: xinqiyang
Author-email: xinqiyang@gmail.com
License: UNKNOWN
Platform: UNKNOWN
Classifier: Programming Language :: Python :: 3
Classifier: License :: OSI Approved :: MIT License
Classifier: Operating System :: OS Independent
Requires-Dist: pandas
Requires-Dist: requests
